pinotdb/__init__.py
pinotdb/db.py
pinotdb/exceptions.py
pinotdb/keywords.py
pinotdb/sqlalchemy.py
pinotdb-5.5.0.dist-info/LICENSE
pinotdb-5.5.0.dist-info/METADATA
pinotdb-5.5.0.dist-info/WHEEL
pinotdb-5.5.0.dist-info/entry_points.txt
pinotdb-5.5.0.dist-info/RECORD
