Metadata-Version: 2.1
Name: pinotdb
Version: 5.5.0
Summary: Python DB-API and SQLAlchemy dialect for Pinot.
Home-page: https://github.com/python-pinot-dbapi/pinot-dbapi
License: MIT
Author: Beto Dealmeida
Author-email: beto@dealmeida.net
Requires-Python: >=3.7,<4
Classifier: License :: OSI Approved :: MIT License
Classifier: Programming Language :: Python :: 3
Classifier: Programming Language :: Python :: 3.7
Classifier: Programming Language :: Python :: 3.8
Classifier: Programming Language :: Python :: 3.9
Classifier: Programming Language :: Python :: 3.10
Classifier: Programming Language :: Python :: 3.11
Classifier: Programming Language :: Python :: 3.12
Provides-Extra: sqlalchemy
Requires-Dist: ciso8601 (>=2.1.3,<3.0.0)
Requires-Dist: httpx (>=0.23.0,<0.28.0)
Requires-Dist: requests (>=2.25.0,<3.0.0) ; extra == "sqlalchemy"
Requires-Dist: sqlalchemy (>=1.4,<2) ; extra == "sqlalchemy"
